src/__init__.py
src/__main__.py
src/settings.py
src/shapes.py
src/style.css
src/tests/__init__.py
src/tests/test_shapes.py
src/tetris.py
pytetris_101-0.0.2.dist-info/LICENSE
pytetris_101-0.0.2.dist-info/METADATA
pytetris_101-0.0.2.dist-info/WHEEL
pytetris_101-0.0.2.dist-info/entry_points.txt
pytetris_101-0.0.2.dist-info/RECORD
