Metadata-Version: 2.1
Name: pytetris-101
Version: 0.0.2
Summary: 
Author: Sergey Royz
Author-email: zjor.se@gmail.com
Requires-Python: >=3.11,<4.0
Classifier: Programming Language :: Python :: 3
Classifier: Programming Language :: Python :: 3.11
Requires-Dist: pytest (>=7.4.0,<8.0.0)
Requires-Dist: textual (>=0.30.0,<0.31.0)
